msnexport/MSNParser.py
msnexport/PDFExporter.py
msnexport/__init__.py
msnexport/cli.py
msnexport-0.2.dist-info/LICENSE
msnexport-0.2.dist-info/METADATA
msnexport-0.2.dist-info/WHEEL
msnexport-0.2.dist-info/entry_points.txt
msnexport-0.2.dist-info/top_level.txt
msnexport-0.2.dist-info/RECORD
