Metadata-Version: 2.1
Name: msnexport
Version: 0.2
Summary: Export your old xml MSN history to pdf.
Home-page: https://github.com/charles-marceau/msnexport
Author: Charles Marceau
Author-email: charlesmarceau3@gmail.com
License: MIT
Classifier: Programming Language :: Python :: 3.7
License-File: LICENSE
Requires-Dist: beautifulsoup4
Requires-Dist: click
Requires-Dist: lxml
Requires-Dist: reportlab
